Metadata-Version: 1.0
Name: slatmet
Version: 2.0
Summary: Weather forecast data
Home-page: UNKNOWN
Author: Martin Slater
Author-email: martinhslater@gmail.com
License: MIT
Keywords: weather,forecast,openweather
Platform: UNKNOWN
